pylingdocs_gui/__init__.py
pylingdocs_gui/cli.py
pylingdocs_gui/editor.py
pylingdocs_gui-0.0.2.dist-info/LICENSE
pylingdocs_gui-0.0.2.dist-info/METADATA
pylingdocs_gui-0.0.2.dist-info/WHEEL
pylingdocs_gui-0.0.2.dist-info/entry_points.txt
pylingdocs_gui-0.0.2.dist-info/top_level.txt
pylingdocs_gui-0.0.2.dist-info/RECORD
